flask_mailman/__init__.py
flask_mailman/backends/__init__.py
flask_mailman/backends/base.py
flask_mailman/backends/console.py
flask_mailman/backends/dummy.py
flask_mailman/backends/file.py
flask_mailman/backends/locmem.py
flask_mailman/backends/smtp.py
flask_mailman/message.py
flask_mailman/utils.py
flask_mailman-1.1.0.dist-info/LICENSE
flask_mailman-1.1.0.dist-info/METADATA
flask_mailman-1.1.0.dist-info/WHEEL
flask_mailman-1.1.0.dist-info/RECORD
