Metadata-Version: 2.1
Name: flask-mailman
Version: 1.1.0
Summary: Porting Django's email implementation to your Flask applications.
Home-page: https://github.com/waynerv/flask-mailman
License: BSD-3-Clause
Keywords: flask,mail,smtp,flask-mail
Author: Waynerv
Author-email: ampedee@gmail.com
Requires-Python: >=3.7,<4.0
Classifier: Development Status :: 4 - Beta
Classifier: Framework :: Flask
Classifier: Intended Audience :: Developers
Classifier: License :: OSI Approved :: BSD License
Classifier: Programming Language :: Python :: 3
Classifier: Programming Language :: Python :: 3.7
Classifier: Programming Language :: Python :: 3.8
Classifier: Programming Language :: Python :: 3.9
Classifier: Programming Language :: Python :: 3.10
Classifier: Programming Language :: Python :: 3.11
Classifier: Programming Language :: Python :: 3.12
Classifier: Topic :: Communications :: Email
Classifier: Topic :: Software Development :: Build Tools
Provides-Extra: dev
Provides-Extra: doc
Provides-Extra: test
Requires-Dist: aiosmtpd (>=1.4.4.post2,<2.0.0) ; extra == "test"
Requires-Dist: black ; extra == "test"
Requires-Dist: bump2version ; extra == "dev"
Requires-Dist: flake8 ; extra == "test"
Requires-Dist: flask (>=1.0)
Requires-Dist: isort ; extra == "test"
Requires-Dist: mkdocs ; extra == "doc"
Requires-Dist: mkdocs-autorefs ; extra == "doc"
Requires-Dist: mkdocs-include-markdown-plugin ; extra == "doc"
Requires-Dist: mkdocs-material ; extra == "doc"
Requires-Dist: mkdocs-material-extensions ; extra == "doc"
Requires-Dist: mkdocstrings ; extra == "doc"
Requires-Dist: pip ; extra == "dev"
Requires-Dist: pre-commit ; extra == "dev"
Requires-Dist: pytest ; extra == "test"
Requires-Dist: pytest-cov ; extra == "test"
Requires-Dist: toml ; extra == "dev"
Requires-Dist: tox ; extra == "dev"
Requires-Dist: twine ; extra == "dev"
Requires-Dist: virtualenv ; extra == "dev"
Project-URL: Repository, https://github.com/waynerv/flask-mailman
